xmvi/__init__.py
xmvi/insights.py
xmvi-0.0.1.dist-info/METADATA
xmvi-0.0.1.dist-info/WHEEL
xmvi-0.0.1.dist-info/licenses/LICENSE
xmvi-0.0.1.dist-info/RECORD
