Metadata-Version: 2.3
Name: xmvi
Version: 0.0.1
Summary: XMPro Vector Insight is a Python library for analyzing and visualizing embedding data. It provides tools for calculating various similarity measures (cosine, Euclidean, inner product) between embeddings and reference vectors, applying different scaling techniques, and performing basic statistical analysis on embedding data. The library is designed with flexibility in mind, allowing for easy extension and customization of its core functionalities.
Project-URL: Homepage, https://github.com/pypa/sampleproject
Project-URL: Issues, https://github.com/pypa/sampleproject/issues
Author-email: Jaun van Heerden <jvh@xmpro.com>
License-File: LICENSE
Classifier: License :: OSI Approved :: MIT License
Classifier: Operating System :: OS Independent
Classifier: Programming Language :: Python :: 3
Requires-Python: >=3.8
Requires-Dist: numpy
Requires-Dist: scikit-learn
